{"bpm": 117.45383522727273, "notes": [{"time": 1.3003174603174603, "lane": 1, "length": 0.0, "hit": false}, {"time": 1.555736961451247, "lane": 1, "length": 0.0, "hit": false}, {"time": 1.811156462585034, "lane": 0, "length": 0.0, "hit": false}, {"time": 3.5062131519274375, "lane": 0, "length": 0.0, "hit": false}, {"time": 3.7616326530612243, "lane": 0, "length": 0.0, "hit": false}, {"time": 4.017052154195011, "lane": 1, "length": 0.0, "hit": false}, {"time": 4.272471655328798, "lane": 1, "length": 0.0, "hit": false}, {"time": 4.620770975056689, "lane": 0, "length": 0.0, "hit": false}, {"time": 4.96907029478458, "lane": 0, "length": 0.0, "hit": false}, {"time": 5.642448979591837, "lane": 0, "length": 0.0, "hit": false}, {"time": 5.990748299319728, "lane": 0, "length": 0.0, "hit": false}, {"time": 6.246167800453515, "lane": 0, "length": 0.0, "hit": false}, {"time": 6.757006802721088, "lane": 0, "length": 0.0, "hit": false}, {"time": 7.012426303854875, "lane": 0, "length": 0.0, "hit": false}, {"time": 7.360725623582766, "lane": 0, "length": 0.0, "hit": false}, {"time": 7.616145124716553, "lane": 0, "length": 0.0, "hit": false}, {"time": 7.87156462585034, "lane": 0, "length": 0.0, "hit": false}, {"time": 8.126984126984127, "lane": 0, "length": 0.0, "hit": false}, {"time": 8.382403628117913, "lane": 0, "length": 0.0, "hit": false}, {"time": 8.6378231292517, "lane": 0, "length": 0.0, "hit": false}, {"time": 8.986122448979591, "lane": 1, "length": 0.0, "hit": false}, {"time": 9.241541950113378, "lane": 1, "length": 0.0, "hit": false}, {"time": 9.496961451247165, "lane": 0, "length": 0.0, "hit": false}, {"time": 9.752380952380953, "lane": 0, "length": 0.0, "hit": false}, {"time": 10.425759637188209, "lane": 0, "length": 0.0, "hit": false}, {"time": 10.7740589569161, "lane": 0, "length": 0.0, "hit": false}, {"time": 11.447437641723356, "lane": 0, "length": 0.0, "hit": false}, {"time": 11.795736961451247, "lane": 0, "length": 0.0, "hit": false}, {"time": 12.144036281179138, "lane": 0, "length": 0.0, "hit": false}, {"time": 12.817414965986394, "lane": 0, "length": 0.0, "hit": false}, {"time": 13.165714285714285, "lane": 0, "length": 0.0, "hit": false}, {"time": 13.769433106575963, "lane": 1, "length": 0.0, "hit": false}, {"time": 14.187392290249432, "lane": 0, "length": 0.0, "hit": false}, {"time": 14.535691609977324, "lane": 0, "length": 0.0, "hit": false}, {"time": 15.209070294784581, "lane": 0, "length": 0.0, "hit": false}, {"time": 15.557369614512472, "lane": 0, "length": 0.0, "hit": false}, {"time": 16.057369614512474, "lane": 2, "length": 1.2291156462585011, "hit": false}, {"time": 16.057369614512474, "lane": 0, "length": 1.7399546485260746, "hit": false}, {"time": 16.057369614512474, "lane": 2, "length": 1.9953741496598614, "hit": false}, {"time": 16.057369614512474, "lane": 0, "length": 2.3436734693877543, "hit": false}, {"time": 16.057369614512474, "lane": 2, "length": 2.761632653061225, "hit": false}, {"time": 19.319002267573698, "lane": 1, "length": 0.0, "hit": false}, {"time": 19.819002267573698, "lane": 3, "length": 1.7399546485260764, "hit": false}, {"time": 19.819002267573698, "lane": 1, "length": 2.088253968253966, "hit": false}, {"time": 19.819002267573698, "lane": 3, "length": 2.4365532879818588, "hit": false}, {"time": 19.819002267573698, "lane": 1, "length": 2.7616326530612234, "hit": false}, {"time": 19.819002267573698, "lane": 3, "length": 3.0, "hit": false}, {"time": 19.819002267573698, "lane": 1, "length": 3.0, "hit": false}, {"time": 19.819002267573698, "lane": 3, "length": 3.0, "hit": false}, {"time": 24.102312925170068, "lane": 1, "length": 0.0, "hit": false}, {"time": 26.006349206349206, "lane": 1, "length": 0.0, "hit": false}, {"time": 27.515646258503402, "lane": 0, "length": 0.0, "hit": false}, {"time": 27.88716553287982, "lane": 1, "length": 0.0, "hit": false}, {"time": 28.38716553287982, "lane": 3, "length": 1.043356009070294, "hit": false}, {"time": 28.38716553287982, "lane": 1, "length": 1.3684353741496587, "hit": false}, {"time": 28.38716553287982, "lane": 3, "length": 1.716734693877548, "hit": false}, {"time": 28.38716553287982, "lane": 1, "length": 2.065034013605441, "hit": false}, {"time": 28.38716553287982, "lane": 3, "length": 2.4133333333333304, "hit": false}, {"time": 28.38716553287982, "lane": 1, "length": 2.9241723356009075, "hit": false}, {"time": 28.38716553287982, "lane": 3, "length": 3.0, "hit": false}, {"time": 28.38716553287982, "lane": 1, "length": 3.0, "hit": false}, {"time": 32.670476190476194, "lane": 0, "length": 0.0, "hit": false}, {"time": 33.18131519274377, "lane": 1, "length": 0.0, "hit": false}, {"time": 34.5512925170068, "lane": 0, "length": 0.0, "hit": false}, {"time": 35.57297052154195, "lane": 1, "length": 0.0, "hit": false}, {"time": 35.92126984126984, "lane": 0, "length": 0.0, "hit": false}, {"time": 36.94294784580499, "lane": 0, "length": 0.0, "hit": false}, {"time": 37.964625850340134, "lane": 1, "length": 0.0, "hit": false}, {"time": 38.31292517006803, "lane": 0, "length": 0.0, "hit": false}, {"time": 39.334603174603174, "lane": 0, "length": 0.0, "hit": false}, {"time": 39.68290249433107, "lane": 0, "length": 0.0, "hit": false}, {"time": 40.35628117913832, "lane": 0, "length": 0.0, "hit": false}, {"time": 41.72625850340136, "lane": 0, "length": 0.0, "hit": false}, {"time": 42.74793650793651, "lane": 0, "length": 0.0, "hit": false}, {"time": 43.51419501133787, "lane": 1, "length": 0.0, "hit": false}, {"time": 44.11791383219955, "lane": 0, "length": 0.0, "hit": false}, {"time": 44.46621315192744, "lane": 0, "length": 0.0, "hit": false}, {"time": 45.139591836734695, "lane": 0, "length": 0.0, "hit": false}, {"time": 45.48789115646259, "lane": 0, "length": 0.0, "hit": false}, {"time": 45.836190476190474, "lane": 1, "length": 0.0, "hit": false}, {"time": 46.16126984126984, "lane": 1, "length": 0.0, "hit": false}, {"time": 46.509569160997735, "lane": 0, "length": 0.0, "hit": false}, {"time": 46.85786848072562, "lane": 0, "length": 0.0, "hit": false}, {"time": 47.53124716553288, "lane": 0, "length": 0.0, "hit": false}, {"time": 47.87954648526077, "lane": 0, "length": 0.0, "hit": false}, {"time": 48.22784580498866, "lane": 1, "length": 0.0, "hit": false}, {"time": 48.55292517006803, "lane": 1, "length": 0.0, "hit": false}, {"time": 48.901224489795915, "lane": 0, "length": 0.0, "hit": false}, {"time": 49.24952380952381, "lane": 0, "length": 0.0, "hit": false}, {"time": 49.92290249433107, "lane": 0, "length": 0.0, "hit": false}, {"time": 50.271201814058955, "lane": 0, "length": 0.0, "hit": false}, {"time": 50.61950113378685, "lane": 1, "length": 0.0, "hit": false}, {"time": 50.944580498866216, "lane": 1, "length": 0.0, "hit": false}, {"time": 51.2928798185941, "lane": 0, "length": 0.0, "hit": false}, {"time": 51.641179138321995, "lane": 0, "length": 0.0, "hit": false}, {"time": 52.31455782312925, "lane": 0, "length": 0.0, "hit": false}, {"time": 52.66285714285714, "lane": 0, "length": 0.0, "hit": false}, {"time": 53.011156462585035, "lane": 1, "length": 0.0, "hit": false}, {"time": 53.336235827664396, "lane": 1, "length": 0.0, "hit": false}, {"time": 53.68453514739229, "lane": 0, "length": 0.0, "hit": false}, {"time": 54.543673469387755, "lane": 0, "length": 0.0, "hit": false}, {"time": 55.40281179138322, "lane": 1, "length": 0.0, "hit": false}, {"time": 56.076190476190476, "lane": 0, "length": 0.0, "hit": false}, {"time": 56.42448979591837, "lane": 0, "length": 0.0, "hit": false}, {"time": 57.608707482993196, "lane": 0, "length": 0.0, "hit": false}, {"time": 57.95700680272109, "lane": 0, "length": 0.0, "hit": false}, {"time": 58.30530612244898, "lane": 1, "length": 0.0, "hit": false}, {"time": 58.816145124716556, "lane": 0, "length": 0.0, "hit": false}, {"time": 59.8378231292517, "lane": 0, "length": 0.0, "hit": false}, {"time": 61.207800453514736, "lane": 0, "length": 0.0, "hit": false}, {"time": 61.707800453514736, "lane": 2, "length": 1.066575963718826, "hit": false}, {"time": 61.707800453514736, "lane": 0, "length": 1.391655328798187, "hit": false}, {"time": 63.59945578231292, "lane": 1, "length": 0.0, "hit": false}, {"time": 64.62113378684808, "lane": 0, "length": 0.0, "hit": false}, {"time": 65.12113378684808, "lane": 2, "length": 3.0, "hit": false}, {"time": 65.12113378684808, "lane": 0, "length": 3.0, "hit": false}, {"time": 65.12113378684808, "lane": 2, "length": 3.0, "hit": false}, {"time": 65.12113378684808, "lane": 0, "length": 3.0, "hit": false}, {"time": 65.12113378684808, "lane": 2, "length": 3.0, "hit": false}, {"time": 89.42004535147392, "lane": 0, "length": 0.0, "hit": false}, {"time": 89.93088435374149, "lane": 1, "length": 0.0, "hit": false}, {"time": 90.27918367346939, "lane": 0, "length": 0.0, "hit": false}, {"time": 91.30086167800454, "lane": 0, "length": 0.0, "hit": false}, {"time": 92.32253968253968, "lane": 1, "length": 0.0, "hit": false}, {"time": 92.67083900226757, "lane": 0, "length": 0.0, "hit": false}, {"time": 93.17083900226757, "lane": 2, "length": 3.0, "hit": false}, {"time": 93.17083900226757, "lane": 0, "length": 3.0, "hit": false}, {"time": 93.17083900226757, "lane": 2, "length": 3.0, "hit": false}, {"time": 97.29160997732426, "lane": 1, "length": 0.0, "hit": false}, {"time": 97.66312925170068, "lane": 0, "length": 0.0, "hit": false}, {"time": 98.61514739229025, "lane": 1, "length": 0.0, "hit": false}, {"time": 99.2885260770975, "lane": 0, "length": 0.0, "hit": false}, {"time": 99.93868480725624, "lane": 1, "length": 0.0, "hit": false}, {"time": 100.2637641723356, "lane": 1, "length": 0.0, "hit": false}, {"time": 100.91392290249433, "lane": 0, "length": 0.0, "hit": false}, {"time": 101.88916099773243, "lane": 0, "length": 0.0, "hit": false}, {"time": 102.19102040816327, "lane": 0, "length": 0.0, "hit": false}, {"time": 103.76997732426304, "lane": 0, "length": 0.0, "hit": false}, {"time": 104.07183673469387, "lane": 0, "length": 0.0, "hit": false}, {"time": 104.37369614512471, "lane": 0, "length": 0.0, "hit": false}, {"time": 104.67555555555556, "lane": 0, "length": 0.0, "hit": false}, {"time": 104.9774149659864, "lane": 1, "length": 0.0, "hit": false}, {"time": 106.7653514739229, "lane": 0, "length": 0.0, "hit": false}, {"time": 107.06721088435374, "lane": 0, "length": 0.0, "hit": false}, {"time": 107.36907029478458, "lane": 1, "length": 0.0, "hit": false}, {"time": 107.94956916099773, "lane": 1, "length": 0.0, "hit": false}, {"time": 108.50684807256236, "lane": 0, "length": 0.0, "hit": false}, {"time": 109.06412698412699, "lane": 0, "length": 0.0, "hit": false}, {"time": 109.62140589569161, "lane": 0, "length": 0.0, "hit": false}, {"time": 110.17868480725623, "lane": 0, "length": 0.0, "hit": false}, {"time": 110.99138321995464, "lane": 0, "length": 0.0, "hit": false}, {"time": 111.24680272108843, "lane": 0, "length": 0.0, "hit": false}, {"time": 111.80408163265307, "lane": 0, "length": 0.0, "hit": false}, {"time": 112.05950113378685, "lane": 0, "length": 0.0, "hit": false}, {"time": 112.31492063492064, "lane": 0, "length": 0.0, "hit": false}, {"time": 112.57034013605443, "lane": 0, "length": 0.0, "hit": false}, {"time": 112.82575963718821, "lane": 0, "length": 0.0, "hit": false}, {"time": 113.081179138322, "lane": 0, "length": 0.0, "hit": false}, {"time": 113.33659863945579, "lane": 0, "length": 0.0, "hit": false}, {"time": 113.59201814058957, "lane": 0, "length": 0.0, "hit": false}, {"time": 113.84743764172336, "lane": 0, "length": 0.0, "hit": false}, {"time": 114.34743764172336, "lane": 2, "length": 1.159455782312918, "hit": false}, {"time": 114.34743764172336, "lane": 0, "length": 1.4148752834467047, "hit": false}, {"time": 114.34743764172336, "lane": 2, "length": 2.877732426303851, "hit": false}, {"time": 114.34743764172336, "lane": 0, "length": 3.0, "hit": false}, {"time": 118.58430839002267, "lane": 0, "length": 0.0, "hit": false}, {"time": 119.08430839002267, "lane": 2, "length": 1.2291156462585064, "hit": false}, {"time": 120.81342403628118, "lane": 0, "length": 0.0, "hit": false}, {"time": 121.31342403628118, "lane": 2, "length": 1.3452154195011303, "hit": false}, {"time": 123.1586394557823, "lane": 0, "length": 0.0, "hit": false}, {"time": 123.4140589569161, "lane": 0, "length": 0.0, "hit": false}, {"time": 124.78403628117914, "lane": 0, "length": 0.0, "hit": false}, {"time": 125.29487528344671, "lane": 0, "length": 0.0, "hit": false}, {"time": 125.6431746031746, "lane": 0, "length": 0.0, "hit": false}, {"time": 126.1431746031746, "lane": 2, "length": 1.7399546485260942, "hit": false}, {"time": 126.1431746031746, "lane": 0, "length": 3.0, "hit": false}, {"time": 126.1431746031746, "lane": 2, "length": 3.0, "hit": false}, {"time": 130.33360544217686, "lane": 0, "length": 0.0, "hit": false}, {"time": 132.00544217687076, "lane": 0, "length": 0.0, "hit": false}, {"time": 132.50544217687076, "lane": 2, "length": 1.1826757369614427, "hit": false}, {"time": 132.50544217687076, "lane": 0, "length": 1.6935147392290162, "hit": false}, {"time": 132.50544217687076, "lane": 2, "length": 1.948934240362803, "hit": false}, {"time": 134.95437641723356, "lane": 1, "length": 0.0, "hit": false}, {"time": 135.20979591836735, "lane": 1, "length": 0.0, "hit": false}, {"time": 135.46521541950113, "lane": 1, "length": 0.0, "hit": false}, {"time": 135.72063492063492, "lane": 0, "length": 0.0, "hit": false}, {"time": 136.90485260770976, "lane": 0, "length": 0.0, "hit": false}, {"time": 137.25315192743764, "lane": 0, "length": 0.0, "hit": false}, {"time": 137.60145124716553, "lane": 1, "length": 0.0, "hit": false}, {"time": 138.2748299319728, "lane": 0, "length": 0.0, "hit": false}, {"time": 138.62312925170068, "lane": 0, "length": 0.0, "hit": false}, {"time": 139.64480725623582, "lane": 0, "length": 0.0, "hit": false}, {"time": 139.9931065759637, "lane": 1, "length": 0.0, "hit": false}, {"time": 140.66648526077097, "lane": 0, "length": 0.0, "hit": false}, {"time": 141.01478458049885, "lane": 0, "length": 0.0, "hit": false}, {"time": 141.68816326530612, "lane": 0, "length": 0.0, "hit": false}, {"time": 142.036462585034, "lane": 0, "length": 0.0, "hit": false}, {"time": 143.05814058956915, "lane": 0, "length": 0.0, "hit": false}, {"time": 143.40643990929706, "lane": 0, "length": 0.0, "hit": false}, {"time": 144.4281179138322, "lane": 0, "length": 0.0, "hit": false}, {"time": 145.10149659863944, "lane": 0, "length": 0.0, "hit": false}, {"time": 145.79809523809524, "lane": 0, "length": 0.0, "hit": false}, {"time": 146.4714739229025, "lane": 0, "length": 0.0, "hit": false}, {"time": 146.9714739229025, "lane": 2, "length": 1.0665759637188046, "hit": false}, {"time": 146.9714739229025, "lane": 0, "length": 1.4148752834466904, "hit": false}, {"time": 146.9714739229025, "lane": 2, "length": 1.7631746031746047, "hit": false}, {"time": 146.9714739229025, "lane": 0, "length": 2.0882539682539516, "hit": false}, {"time": 146.9714739229025, "lane": 2, "length": 2.4365532879818375, "hit": false}, {"time": 146.9714739229025, "lane": 0, "length": 2.7848526077097517, "hit": false}, {"time": 146.9714739229025, "lane": 2, "length": 3.0, "hit": false}, {"time": 150.5814058956916, "lane": 1, "length": 0.0, "hit": false}, {"time": 151.0814058956916, "lane": 3, "length": 1.066575963718833, "hit": false}, {"time": 151.0814058956916, "lane": 1, "length": 1.4148752834467189, "hit": false}, {"time": 151.0814058956916, "lane": 3, "length": 1.7399546485260942, "hit": false}, {"time": 151.0814058956916, "lane": 1, "length": 2.08825396825398, "hit": false}, {"time": 151.0814058956916, "lane": 3, "length": 2.436553287981866, "hit": false}, {"time": 151.0814058956916, "lane": 1, "length": 2.7848526077097517, "hit": false}, {"time": 154.36625850340135, "lane": 1, "length": 0.0, "hit": false}, {"time": 155.364716553288, "lane": 1, "length": 0.0, "hit": false}, {"time": 156.75791383219953, "lane": 1, "length": 0.0, "hit": false}, {"time": 157.25791383219953, "lane": 3, "length": 1.043356009070294, "hit": false}, {"time": 157.25791383219953, "lane": 1, "length": 1.3684353741496693, "hit": false}, {"time": 157.25791383219953, "lane": 3, "length": 1.7167346938775552, "hit": false}, {"time": 157.25791383219953, "lane": 1, "length": 2.065034013605441, "hit": false}, {"time": 157.25791383219953, "lane": 3, "length": 2.4133333333333553, "hit": false}, {"time": 157.25791383219953, "lane": 1, "length": 2.738412698412702, "hit": false}, {"time": 157.25791383219953, "lane": 3, "length": 3.0, "hit": false}, {"time": 157.25791383219953, "lane": 1, "length": 3.0, "hit": false}, {"time": 157.25791383219953, "lane": 3, "length": 3.0, "hit": false}, {"time": 157.25791383219953, "lane": 1, "length": 3.0, "hit": false}, {"time": 162.0520634920635, "lane": 1, "length": 0.0, "hit": false}, {"time": 162.40036281179138, "lane": 0, "length": 0.0, "hit": false}, {"time": 162.74866213151927, "lane": 0, "length": 0.0, "hit": false}, {"time": 163.42204081632653, "lane": 0, "length": 0.0, "hit": false}, {"time": 163.9328798185941, "lane": 0, "length": 0.0, "hit": false}, {"time": 164.44371882086168, "lane": 1, "length": 0.0, "hit": false}, {"time": 164.79201814058956, "lane": 0, "length": 0.0, "hit": false}, {"time": 165.8136961451247, "lane": 0, "length": 0.0, "hit": false}, {"time": 166.1619954648526, "lane": 0, "length": 0.0, "hit": false}, {"time": 166.83537414965986, "lane": 1, "length": 0.0, "hit": false}, {"time": 167.18367346938774, "lane": 0, "length": 0.0, "hit": false}, {"time": 168.04281179138323, "lane": 0, "length": 0.0, "hit": false}, {"time": 168.5536507936508, "lane": 0, "length": 0.0, "hit": false}, {"time": 169.57532879818595, "lane": 0, "length": 0.0, "hit": false}, {"time": 169.92362811791384, "lane": 0, "length": 0.0, "hit": false}, {"time": 170.5970068027211, "lane": 0, "length": 0.0, "hit": false}, {"time": 170.94530612244898, "lane": 0, "length": 0.0, "hit": false}, {"time": 171.61868480725624, "lane": 0, "length": 0.0, "hit": false}, {"time": 171.96698412698413, "lane": 0, "length": 0.0, "hit": false}, {"time": 172.31528344671202, "lane": 0, "length": 0.0, "hit": false}, {"time": 172.98866213151928, "lane": 0, "length": 0.0, "hit": false}, {"time": 173.33696145124716, "lane": 0, "length": 0.0, "hit": false}, {"time": 174.01034013605442, "lane": 0, "length": 0.0, "hit": false}, {"time": 174.3586394557823, "lane": 0, "length": 0.0, "hit": false}, {"time": 174.7069387755102, "lane": 0, "length": 0.0, "hit": false}, {"time": 175.38031746031746, "lane": 0, "length": 0.0, "hit": false}, {"time": 175.72861678004534, "lane": 0, "length": 0.0, "hit": false}, {"time": 176.4019954648526, "lane": 0, "length": 0.0, "hit": false}, {"time": 176.7502947845805, "lane": 0, "length": 0.0, "hit": false}, {"time": 177.0985941043084, "lane": 1, "length": 0.0, "hit": false}, {"time": 177.42367346938775, "lane": 1, "length": 0.0, "hit": false}, {"time": 177.77197278911564, "lane": 0, "length": 0.0, "hit": false}, {"time": 178.12027210884355, "lane": 0, "length": 0.0, "hit": false}, {"time": 178.79365079365078, "lane": 0, "length": 0.0, "hit": false}, {"time": 179.1419501133787, "lane": 0, "length": 0.0, "hit": false}, {"time": 179.49024943310658, "lane": 1, "length": 0.0, "hit": false}, {"time": 180.16362811791385, "lane": 0, "length": 0.0, "hit": false}, {"time": 180.51192743764173, "lane": 0, "length": 0.0, "hit": false}, {"time": 181.185306122449, "lane": 0, "length": 0.0, "hit": false}, {"time": 181.53360544217688, "lane": 0, "length": 0.0, "hit": false}, {"time": 181.88190476190476, "lane": 1, "length": 0.0, "hit": false}, {"time": 182.20698412698414, "lane": 1, "length": 0.0, "hit": false}, {"time": 182.55528344671202, "lane": 0, "length": 0.0, "hit": false}, {"time": 182.9035827664399, "lane": 0, "length": 0.0, "hit": false}, {"time": 183.57696145124717, "lane": 0, "length": 0.0, "hit": false}, {"time": 183.92526077097506, "lane": 0, "length": 0.0, "hit": false}, {"time": 184.27356009070294, "lane": 1, "length": 0.0, "hit": false}, {"time": 184.9469387755102, "lane": 0, "length": 0.0, "hit": false}, {"time": 185.2952380952381, "lane": 0, "length": 0.0, "hit": false}, {"time": 185.55065759637188, "lane": 0, "length": 0.0, "hit": false}, {"time": 185.80607709750566, "lane": 0, "length": 0.0, "hit": false}, {"time": 186.47945578231293, "lane": 0, "length": 0.0, "hit": false}, {"time": 186.8277551020408, "lane": 0, "length": 0.0, "hit": false}, {"time": 187.50113378684807, "lane": 1, "length": 0.0, "hit": false}, {"time": 187.84943310657596, "lane": 0, "length": 0.0, "hit": false}, {"time": 188.19773242630384, "lane": 0, "length": 0.0, "hit": false}, {"time": 188.8711111111111, "lane": 0, "length": 0.0, "hit": false}, {"time": 189.219410430839, "lane": 0, "length": 0.0, "hit": false}, {"time": 189.5677097505669, "lane": 1, "length": 0.0, "hit": false}, {"time": 189.89278911564625, "lane": 1, "length": 0.0, "hit": false}, {"time": 190.24108843537414, "lane": 0, "length": 0.0, "hit": false}, {"time": 190.58938775510205, "lane": 0, "length": 0.0, "hit": false}], "duration": 191.178231292517, "audio_path": "songs/(aperson) Tranzport/15._(Arkitech)_Tranzport.mp3"}