{"bpm": 107.666015625, "notes": [{"time": 1.207437641723356, "lane": 0, "length": 0.0, "hit": false}, {"time": 1.9736961451247166, "lane": 0, "length": 0.0, "hit": false}, {"time": 3.0882539682539685, "lane": 0, "length": 0.0, "hit": false}, {"time": 4.4117913832199545, "lane": 0, "length": 0.0, "hit": false}, {"time": 4.96907029478458, "lane": 0, "length": 0.0, "hit": false}, {"time": 5.340589569160998, "lane": 1, "length": 0.0, "hit": false}, {"time": 6.849886621315193, "lane": 0, "length": 0.0, "hit": false}, {"time": 7.22140589569161, "lane": 0, "length": 0.0, "hit": false}, {"time": 8.730702947845804, "lane": 1, "length": 0.0, "hit": false}, {"time": 9.102222222222222, "lane": 0, "length": 0.0, "hit": false}, {"time": 10.216780045351474, "lane": 0, "length": 0.0, "hit": false}, {"time": 12.097596371882085, "lane": 0, "length": 0.0, "hit": false}, {"time": 12.445895691609977, "lane": 1, "length": 0.0, "hit": false}, {"time": 13.212154195011339, "lane": 0, "length": 0.0, "hit": false}, {"time": 13.978412698412699, "lane": 0, "length": 0.0, "hit": false}, {"time": 14.349931972789115, "lane": 1, "length": 0.0, "hit": false}, {"time": 15.85922902494331, "lane": 0, "length": 0.0, "hit": false}, {"time": 16.35922902494331, "lane": 2, "length": 1.4148752834467118, "hit": false}, {"time": 16.35922902494331, "lane": 0, "length": 1.7863945578231295, "hit": false}, {"time": 16.35922902494331, "lane": 2, "length": 2.1579138321995472, "hit": false}, {"time": 19.017142857142858, "lane": 0, "length": 0.0, "hit": false}, {"time": 19.783401360544218, "lane": 0, "length": 0.0, "hit": false}, {"time": 20.897959183673468, "lane": 0, "length": 0.0, "hit": false}, {"time": 21.269478458049885, "lane": 0, "length": 0.0, "hit": false}, {"time": 22.77877551020408, "lane": 1, "length": 0.0, "hit": false}, {"time": 23.1502947845805, "lane": 0, "length": 0.0, "hit": false}, {"time": 24.102312925170068, "lane": 1, "length": 0.0, "hit": false}, {"time": 24.473832199546486, "lane": 0, "length": 0.0, "hit": false}, {"time": 25.588390022675735, "lane": 0, "length": 0.0, "hit": false}, {"time": 26.354648526077096, "lane": 0, "length": 0.0, "hit": false}, {"time": 27.46920634920635, "lane": 0, "length": 0.0, "hit": false}, {"time": 28.398004535147393, "lane": 1, "length": 0.0, "hit": false}, {"time": 29.141043083900225, "lane": 1, "length": 0.0, "hit": false}, {"time": 30.464580498866212, "lane": 1, "length": 0.0, "hit": false}, {"time": 31.230839002267572, "lane": 0, "length": 0.0, "hit": false}, {"time": 31.60235827664399, "lane": 0, "length": 0.0, "hit": false}, {"time": 32.71691609977324, "lane": 0, "length": 0.0, "hit": false}, {"time": 34.59773242630386, "lane": 0, "length": 0.0, "hit": false}, {"time": 35.09773242630386, "lane": 2, "length": 1.2523356009070241, "hit": false}, {"time": 35.09773242630386, "lane": 0, "length": 1.6238548752834419, "hit": false}, {"time": 35.09773242630386, "lane": 2, "length": 1.9953741496598596, "hit": false}, {"time": 37.593106575963716, "lane": 0, "length": 0.0, "hit": false}, {"time": 37.964625850340134, "lane": 1, "length": 0.0, "hit": false}, {"time": 38.35936507936508, "lane": 0, "length": 0.0, "hit": false}, {"time": 39.84544217687075, "lane": 0, "length": 0.0, "hit": false}, {"time": 40.79746031746032, "lane": 1, "length": 0.0, "hit": false}, {"time": 41.72625850340136, "lane": 0, "length": 0.0, "hit": false}, {"time": 42.22625850340136, "lane": 2, "length": 3.0, "hit": false}, {"time": 54.45079365079365, "lane": 0, "length": 0.0, "hit": false}, {"time": 55.00807256235828, "lane": 0, "length": 0.0, "hit": false}, {"time": 56.16907029478458, "lane": 0, "length": 0.0, "hit": false}, {"time": 57.35328798185941, "lane": 0, "length": 0.0, "hit": false}, {"time": 58.42140589569161, "lane": 0, "length": 0.0, "hit": false}, {"time": 58.7697052154195, "lane": 0, "length": 0.0, "hit": false}, {"time": 60.441541950113375, "lane": 1, "length": 0.0, "hit": false}, {"time": 61.02204081632653, "lane": 1, "length": 0.0, "hit": false}, {"time": 61.41678004535147, "lane": 0, "length": 0.0, "hit": false}, {"time": 61.765079365079366, "lane": 1, "length": 0.0, "hit": false}, {"time": 63.08861678004535, "lane": 1, "length": 0.0, "hit": false}, {"time": 63.58861678004535, "lane": 3, "length": 1.4148752834467118, "hit": false}, {"time": 63.58861678004535, "lane": 1, "length": 1.8328344671201862, "hit": false}, {"time": 63.58861678004535, "lane": 3, "length": 2.204353741496597, "hit": false}, {"time": 63.58861678004535, "lane": 1, "length": 2.5758730158730216, "hit": false}, {"time": 66.66448979591837, "lane": 0, "length": 0.0, "hit": false}, {"time": 67.01278911564626, "lane": 0, "length": 0.0, "hit": false}, {"time": 67.51278911564626, "lane": 2, "length": 1.275555555555556, "hit": false}, {"time": 67.51278911564626, "lane": 0, "length": 1.73995464852608, "hit": false}, {"time": 67.51278911564626, "lane": 2, "length": 1.9953741496598667, "hit": false}, {"time": 67.51278911564626, "lane": 0, "length": 2.390113378684802, "hit": false}, {"time": 67.51278911564626, "lane": 2, "length": 2.738412698412702, "hit": false}, {"time": 67.51278911564626, "lane": 0, "length": 3.0, "hit": false}, {"time": 67.51278911564626, "lane": 2, "length": 3.0, "hit": false}, {"time": 67.51278911564626, "lane": 0, "length": 3.0, "hit": false}, {"time": 71.91219954648525, "lane": 0, "length": 0.0, "hit": false}, {"time": 72.41219954648525, "lane": 2, "length": 1.066575963718833, "hit": false}, {"time": 72.41219954648525, "lane": 0, "length": 1.4380952380952436, "hit": false}, {"time": 74.3502947845805, "lane": 0, "length": 0.0, "hit": false}, {"time": 74.8502947845805, "lane": 2, "length": 1.0665759637188188, "hit": false}, {"time": 74.8502947845805, "lane": 0, "length": 1.3219954648526056, "hit": false}, {"time": 74.8502947845805, "lane": 2, "length": 1.7863945578231295, "hit": false}, {"time": 77.13668934240363, "lane": 1, "length": 0.0, "hit": false}, {"time": 78.46022675736961, "lane": 1, "length": 0.0, "hit": false}, {"time": 79.04072562358277, "lane": 1, "length": 0.0, "hit": false}, {"time": 80.71256235827664, "lane": 0, "length": 0.0, "hit": false}, {"time": 81.10730158730159, "lane": 1, "length": 0.0, "hit": false}, {"time": 81.478820861678, "lane": 0, "length": 0.0, "hit": false}, {"time": 82.59337868480726, "lane": 0, "length": 0.0, "hit": false}, {"time": 84.47419501133787, "lane": 0, "length": 0.0, "hit": false}, {"time": 85.58875283446712, "lane": 0, "length": 0.0, "hit": false}], "duration": 86.94857142857143, "audio_path": "songs/4-R Hot Damned RETRO/dB soundworks - Super Meat Boy! Soundtrack - 27 Hot Damned RETRO (Ch 4 Warp Zone).ogg"}